odoo/addons/edi_sale_order_import/README.rst
odoo/addons/edi_sale_order_import/__init__.py
odoo/addons/edi_sale_order_import/__manifest__.py
odoo/addons/edi_sale_order_import/hooks.py
odoo/addons/edi_sale_order_import/i18n/edi_sale_order_import.pot
odoo/addons/edi_sale_order_import/i18n/es.po
odoo/addons/edi_sale_order_import/readme/CONTRIBUTORS.rst
odoo/addons/edi_sale_order_import/readme/DESCRIPTION.rst
odoo/addons/edi_sale_order_import/static/description/icon.png
odoo/addons/edi_sale_order_import/static/description/index.html
odoo/addons/edi_sale_order_import/templates/exchange_chatter_msg.xml
odoo/addons/edi_sale_order_import/tests/test_process.py
odoo14_addon_edi_sale_order_import-14.0.2.0.0.dist-info/METADATA
odoo14_addon_edi_sale_order_import-14.0.2.0.0.dist-info/WHEEL
odoo14_addon_edi_sale_order_import-14.0.2.0.0.dist-info/top_level.txt
odoo14_addon_edi_sale_order_import-14.0.2.0.0.dist-info/RECORD
