Metadata-Version: 2.1
Name: odoo14-addon-edi_sale_order_import
Version: 14.0.2.0.0
Summary: MODULE DEPRECATED: use `edi_sale_oca`. Plug sale_order_import into EDI machinery.
Home-page: https://github.com/OCA/edi
Author: Camptocamp,Odoo Community Association (OCA)
Author-email: support@odoo-community.org
License: AGPL-3
Classifier: Programming Language :: Python
Classifier: Framework :: Odoo
Classifier: Framework :: Odoo :: 14.0
Classifier: License :: OSI Approved :: GNU Affero General Public License v3
Classifier: Development Status :: 3 - Alpha
Requires-Python: >=3.6
Requires-Dist: odoo14-addon-edi-sale-oca
Requires-Dist: odoo<14.1dev,>=14.0a
